LBLDataAccess/__init__.py
LBLDataAccess/access_nomis.py
LBLDataAccess/load_geocodes.py
LBLDataAccess/config/config.json
LBLDataAccess/lookups/json_data.json
LBLDataAccess/lookups/2011/Lower_Layer_Super_Output_Area_(2011)_to_Travel_to_Work_Area_(December_2011)_Lookup_in_the_United_Kingdom.csv
LBLDataAccess/lookups/2011/OA_to_LSOA_to_MSOA_to_LAD_(December_2011)_Lookup_in_England_and_Wales.csv
LBLDataAccess/lookups/2011/Output_Area_(2011)_to_Clinical_Commissioning_Group_to_STP_and_NHS_England_(Region)_(April_2020)_Lookup_in_England.csv
LBLDataAccess/lookups/2011/Output_Area_to_LAU2_to_LAU1_to_NUTS3_to_NUTS2_to_NUTS1_(December_2011)_Lookup_in_England_and_Wales.csv
LBLDataAccess/lookups/2011/Output_Area_to_Primary_Care_Organisation_to_Strategic_Health_Authority_(December_2011)_Lookup_in_England_and_Wales.csv
LBLDataAccess/lookups/2011/Output_Area_to_Region_(December_2011)_Lookup_in_England.csv
LBLDataAccess/lookups/2011/Output_Area_to_Ward_to_Local_Authority_District_(December_2011)_Lookup_in_England_and_Wales.csv
LBLDataAccess/lookups/2011/Output_Area_to_Westminster_Parliamentary_Constituency_to_EER_(December_2011)_Lookup_in_England_and_Wales.csv
LBLDataAccess/lookups/2011/Output_Area_to_Workplace_Zone_to_Local_Authority_District_(December_2011)_Lookup_in_England_and_Wales.csv
LBLDataAccess/lookups/2011/WZ_to_BUASD_to_BUA_to_LAD_to_Region_(December_2011)_Lookup_in_England_and_Wales.csv
LBLDataAccess/lookups/2011/Ward_to_Census_Merged_Ward_to_Local_Authority_District_(December_2011)_Lookup_in_England_and_Wales.csv
LBLDataAccess/lookups/2011/Workplace_Zone_to_Middle_Layer_Super_Output_Area_to_Local_Authority_District_(December_2011)_Lookup_in_England_and_Wales.csv
LBLDataAccess/lookups/2011_to_2021/Local_Authority_District_(2011)_to_Local_Authority_District_(2021)_Lookup_for_England_and_Wales.csv
LBLDataAccess/lookups/2011_to_2021_to_2022/LSOA_(2011)_to_LSOA_(2021)_to_LAD_(2022)_Lookup_for_England_and_Wales_(Version_2).csv
LBLDataAccess-0.2.2.dist-info/LICENSE
LBLDataAccess-0.2.2.dist-info/METADATA
LBLDataAccess-0.2.2.dist-info/WHEEL
LBLDataAccess-0.2.2.dist-info/top_level.txt
LBLDataAccess-0.2.2.dist-info/RECORD
